{
  "ar": [
    "splashAdDisclaimer",
    "adLoading",
    "smartCropPresetAuto",
    "smartCropPresetCenter",
    "smartCropPresetFull",
    "smartCropUploadIntroGoogleScanner",
    "smartCropImportReadingProgress",
    "smartCropImportPartialFailure"
  ],

  "de": [
    "splashAdDisclaimer",
    "adLoading",
    "smartCropPresetAuto",
    "smartCropPresetCenter",
    "smartCropPresetFull",
    "smartCropUploadIntroGoogleScanner",
    "smartCropImportReadingProgress",
    "smartCropImportPartialFailure"
  ],

  "es": [
    "splashAdDisclaimer",
    "adLoading",
    "smartCropPresetAuto",
    "smartCropPresetCenter",
    "smartCropPresetFull",
    "smartCropUploadIntroGoogleScanner",
    "smartCropImportReadingProgress",
    "smartCropImportPartialFailure"
  ],

  "fr": [
    "splashAdDisclaimer",
    "adLoading",
    "smartCropPresetAuto",
    "smartCropPresetCenter",
    "smartCropPresetFull",
    "smartCropUploadIntroGoogleScanner",
    "smartCropImportReadingProgress",
    "smartCropImportPartialFailure"
  ],

  "it": [
    "splashAdDisclaimer",
    "adLoading",
    "smartCropPresetAuto",
    "smartCropPresetCenter",
    "smartCropPresetFull",
    "smartCropUploadIntroGoogleScanner",
    "smartCropImportReadingProgress",
    "smartCropImportPartialFailure"
  ],

  "ja": [
    "splashAdDisclaimer",
    "adLoading",
    "smartCropPresetAuto",
    "smartCropPresetCenter",
    "smartCropPresetFull",
    "smartCropUploadIntroGoogleScanner",
    "smartCropImportReadingProgress",
    "smartCropImportPartialFailure"
  ],

  "ko": [
    "splashAdDisclaimer",
    "adLoading",
    "smartCropPresetAuto",
    "smartCropPresetCenter",
    "smartCropPresetFull",
    "smartCropUploadIntroGoogleScanner",
    "smartCropImportReadingProgress",
    "smartCropImportPartialFailure"
  ],

  "pt": [
    "splashAdDisclaimer",
    "adLoading",
    "smartCropPresetAuto",
    "smartCropPresetCenter",
    "smartCropPresetFull",
    "smartCropUploadIntroGoogleScanner",
    "smartCropImportReadingProgress",
    "smartCropImportPartialFailure"
  ],

  "ru": [
    "splashAdDisclaimer",
    "adLoading",
    "smartCropPresetAuto",
    "smartCropPresetCenter",
    "smartCropPresetFull",
    "smartCropUploadIntroGoogleScanner",
    "smartCropImportReadingProgress",
    "smartCropImportPartialFailure"
  ],

  "zh": [
    "splashAdDisclaimer",
    "adLoading",
    "smartCropPresetAuto",
    "smartCropPresetCenter",
    "smartCropPresetFull",
    "smartCropUploadIntroGoogleScanner",
    "smartCropImportReadingProgress",
    "smartCropImportPartialFailure"
  ]
}
